{
  "خامس 1": [
    "حمد بن سعيد الكندي",
    "ماجد بن خلفان الرواحي",
    "ناصر بن راشد الحارثي",
    "خالد بن محمد الشكيلي",
    "هيثم بن عبدالله المعمري",
    "سعيد بن حمد السيابي",
    "أحمد بن سالم القاسمي",
    "يوسف بن سيف الهطالي",
    "راشد بن حمود البلوشي",
    "محمود بن خليفة الحبسي",
    "عبدالله بن محمد الحضرمي",
    "منصور بن سيف النبهاني",
    "بدر بن ناصر العبري",
    "حسن بن خالد الغافري",
    "إبراهيم بن سيف الزدجالي",
    "علي بن سعيد الفارسي",
    "جاسم بن خليفة العوفي",
    "طلال بن حمد السعدي",
    "سعود بن ناصر الحاتمي",
    "سالم بن علي البوسعيدي",
    "حمد بن سعيد الكندي",
    "ماجد بن خلفان الرواحي",
    "ناصر بن راشد الحارثي",
    "خالد بن محمد الشكيلي",
    "هيثم بن عبدالله المعمري",
    "سعيد بن حمد السيابي",
    "أحمد بن سالم القاسمي",
    "يوسف بن سيف الهطالي",
    "راشد بن حمود البلوشي",
    "محمود بن خليفة الحبسي",
    "عبدالله بن محمد الحضرمي",
    "منصور بن سيف النبهاني",
    "بدر بن ناصر العبري",
    "حسن بن خالد الغافري",
    "إبراهيم بن سيف الزدجالي",
    "علي بن سعيد الفارسي",
    "جاسم بن خليفة العوفي"
  ],
  "خامس 2": [
    "حمد بن سعيد الكندي",
    "ماجد بن خلفان الرواحي",
    "ناصر بن راشد الحارثي",
    "خالد بن محمد الشكيلي",
    "هيثم بن عبدالله المعمري",
    "سعيد بن حمد السيابي",
    "أحمد بن سالم القاسمي",
    "يوسف بن سيف الهطالي",
    "راشد بن حمود البلوشي",
    "محمود بن خليفة الحبسي",
    "عبدالله بن محمد الحضرمي",
    "منصور بن سيف النبهاني",
    "بدر بن ناصر العبري",
    "حسن بن خالد الغافري",
    "إبراهيم بن سيف الزدجالي",
    "علي بن سعيد الفارسي",
    "جاسم بن خليفة العوفي",
    "طلال بن حمد السعدي",
    "سعود بن ناصر الحاتمي",
    "سالم بن علي البوسعيدي",
    "حمد بن سعيد الكندي",
    "ماجد بن خلفان الرواحي",
    "ناصر بن راشد الحارثي",
    "خالد بن محمد الشكيلي",
    "هيثم بن عبدالله المعمري",
    "سعيد بن حمد السيابي",
    "أحمد بن سالم القاسمي",
    "يوسف بن سيف الهطالي",
    "راشد بن حمود البلوشي",
    "محمود بن خليفة الحبسي",
    "عبدالله بن محمد الحضرمي",
    "منصور بن سيف النبهاني",
    "بدر بن ناصر العبري",
    "حسن بن خالد الغافري",
    "إبراهيم بن سيف الزدجالي",
    "علي بن سعيد الفارسي",
    "جاسم بن خليفة العوفي",
    "طلال بن حمد السعدي"
  ],
  "خامس 3": [
    "حمد بن سعيد الكندي",
    "ماجد بن خلفان الرواحي",
    "ناصر بن راشد الحارثي",
    "خالد بن محمد الشكيلي",
    "هيثم بن عبدالله المعمري",
    "سعيد بن حمد السيابي",
    "أحمد بن سالم القاسمي",
    "يوسف بن سيف الهطالي",
    "راشد بن حمود البلوشي",
    "محمود بن خليفة الحبسي",
    "عبدالله بن محمد الحضرمي",
    "منصور بن سيف النبهاني",
    "بدر بن ناصر العبري",
    "حسن بن خالد الغافري",
    "إبراهيم بن سيف الزدجالي",
    "علي بن سعيد الفارسي",
    "جاسم بن خليفة العوفي",
    "طلال بن حمد السعدي",
    "سعود بن ناصر الحاتمي",
    "سالم بن علي البوسعيدي",
    "حمد بن سعيد الكندي",
    "ماجد بن خلفان الرواحي",
    "ناصر بن راشد الحارثي",
    "خالد بن محمد الشكيلي",
    "هيثم بن عبدالله المعمري",
    "سعيد بن حمد السيابي",
    "أحمد بن سالم القاسمي",
    "يوسف بن سيف الهطالي",
    "راشد بن حمود البلوشي",
    "محمود بن خليفة الحبسي",
    "عبدالله بن محمد الحضرمي",
    "منصور بن سيف النبهاني",
    "بدر بن ناصر العبري",
    "حسن بن خالد الغافري",
    "إبراهيم بن سيف الزدجالي",
    "علي بن سعيد الفارسي",
    "جاسم بن خليفة العوفي"
  ],
  "خامس 4": [
    "حمد بن سعيد الكندي",
    "ماجد بن خلفان الرواحي",
    "ناصر بن راشد الحارثي",
    "خالد بن محمد الشكيلي",
    "هيثم بن عبدالله المعمري",
    "سعيد بن حمد السيابي",
    "أحمد بن سالم القاسمي",
    "يوسف بن سيف الهطالي",
    "راشد بن حمود البلوشي",
    "محمود بن خليفة الحبسي",
    "عبدالله بن محمد الحضرمي",
    "منصور بن سيف النبهاني",
    "بدر بن ناصر العبري",
    "حسن بن خالد الغافري",
    "إبراهيم بن سيف الزدجالي",
    "علي بن سعيد الفارسي",
    "جاسم بن خليفة العوفي",
    "طلال بن حمد السعدي",
    "سعود بن ناصر الحاتمي",
    "سالم بن علي البوسعيدي",
    "حمد بن سعيد الكندي",
    "ماجد بن خلفان الرواحي",
    "ناصر بن راشد الحارثي",
    "خالد بن محمد الشكيلي",
    "هيثم بن عبدالله المعمري",
    "سعيد بن حمد السيابي",
    "أحمد بن سالم القاسمي",
    "يوسف بن سيف الهطالي",
    "راشد بن حمود البلوشي",
    "محمود بن خليفة الحبسي",
    "عبدالله بن محمد الحضرمي",
    "منصور بن سيف النبهاني",
    "بدر بن ناصر العبري",
    "حسن بن خالد الغافري",
    "إبراهيم بن سيف الزدجالي",
    "علي بن سعيد الفارسي",
    "جاسم بن خليفة العوفي",
    "طلال بن حمد السعدي",
    "سعود بن ناصر الحاتمي"
  ],
  "سادس 1": [
    "حمد بن سعيد الكندي",
    "ماجد بن خلفان الرواحي",
    "ناصر بن راشد الحارثي",
    "خالد بن محمد الشكيلي",
    "هيثم بن عبدالله المعمري",
    "سعيد بن حمد السيابي",
    "أحمد بن سالم القاسمي",
    "يوسف بن سيف الهطالي",
    "راشد بن حمود البلوشي",
    "محمود بن خليفة الحبسي",
    "عبدالله بن محمد الحضرمي",
    "منصور بن سيف النبهاني",
    "بدر بن ناصر العبري",
    "حسن بن خالد الغافري",
    "إبراهيم بن سيف الزدجالي",
    "علي بن سعيد الفارسي",
    "جاسم بن خليفة العوفي",
    "طلال بن حمد السعدي",
    "سعود بن ناصر الحاتمي",
    "سالم بن علي البوسعيدي",
    "حمد بن سعيد الكندي",
    "ماجد بن خلفان الرواحي",
    "ناصر بن راشد الحارثي",
    "خالد بن محمد الشكيلي",
    "هيثم بن عبدالله المعمري",
    "سعيد بن حمد السيابي",
    "أحمد بن سالم القاسمي",
    "يوسف بن سيف الهطالي",
    "راشد بن حمود البلوشي",
    "محمود بن خليفة الحبسي",
    "عبدالله بن محمد الحضرمي",
    "منصور بن سيف النبهاني",
    "بدر بن ناصر العبري",
    "حسن بن خالد الغافري",
    "إبراهيم بن سيف الزدجالي",
    "علي بن سعيد الفارسي"
  ],
  "سادس 2": [
    "حمد بن سعيد الكندي",
    "ماجد بن خلفان الرواحي",
    "ناصر بن راشد الحارثي",
    "خالد بن محمد الشكيلي",
    "هيثم بن عبدالله المعمري",
    "سعيد بن حمد السيابي",
    "أحمد بن سالم القاسمي",
    "يوسف بن سيف الهطالي",
    "راشد بن حمود البلوشي",
    "محمود بن خليفة الحبسي",
    "عبدالله بن محمد الحضرمي",
    "منصور بن سيف النبهاني",
    "بدر بن ناصر العبري",
    "حسن بن خالد الغافري",
    "إبراهيم بن سيف الزدجالي",
    "علي بن سعيد الفارسي",
    "جاسم بن خليفة العوفي",
    "طلال بن حمد السعدي",
    "سعود بن ناصر الحاتمي",
    "سالم بن علي البوسعيدي",
    "حمد بن سعيد الكندي",
    "ماجد بن خلفان الرواحي",
    "ناصر بن راشد الحارثي",
    "خالد بن محمد الشكيلي",
    "هيثم بن عبدالله المعمري",
    "سعيد بن حمد السيابي",
    "أحمد بن سالم القاسمي",
    "يوسف بن سيف الهطالي",
    "راشد بن حمود البلوشي",
    "محمود بن خليفة الحبسي",
    "عبدالله بن محمد الحضرمي",
    "منصور بن سيف النبهاني",
    "بدر بن ناصر العبري",
    "حسن بن خالد الغافري",
    "إبراهيم بن سيف الزدجالي",
    "علي بن سعيد الفارسي"
  ],
  "سادس 3": [
    "حمد بن سعيد الكندي",
    "ماجد بن خلفان الرواحي",
    "ناصر بن راشد الحارثي",
    "خالد بن محمد الشكيلي",
    "هيثم بن عبدالله المعمري",
    "سعيد بن حمد السيابي",
    "أحمد بن سالم القاسمي",
    "يوسف بن سيف الهطالي",
    "راشد بن حمود البلوشي",
    "محمود بن خليفة الحبسي",
    "عبدالله بن محمد الحضرمي",
    "منصور بن سيف النبهاني",
    "بدر بن ناصر العبري",
    "حسن بن خالد الغافري",
    "إبراهيم بن سيف الزدجالي",
    "علي بن سعيد الفارسي",
    "جاسم بن خليفة العوفي",
    "طلال بن حمد السعدي",
    "سعود بن ناصر الحاتمي",
    "سالم بن علي البوسعيدي",
    "حمد بن سعيد الكندي",
    "ماجد بن خلفان الرواحي",
    "ناصر بن راشد الحارثي",
    "خالد بن محمد الشكيلي",
    "هيثم بن عبدالله المعمري",
    "سعيد بن حمد السيابي",
    "أحمد بن سالم القاسمي",
    "يوسف بن سيف الهطالي",
    "راشد بن حمود البلوشي",
    "محمود بن خليفة الحبسي",
    "عبدالله بن محمد الحضرمي",
    "منصور بن سيف النبهاني",
    "بدر بن ناصر العبري",
    "حسن بن خالد الغافري",
    "إبراهيم بن سيف الزدجالي",
    "علي بن سعيد الفارسي",
    "جاسم بن خليفة العوفي"
  ],
  "سادس 4": [
    "حمد بن سعيد الكندي",
    "ماجد بن خلفان الرواحي",
    "ناصر بن راشد الحارثي",
    "خالد بن محمد الشكيلي",
    "هيثم بن عبدالله المعمري",
    "سعيد بن حمد السيابي",
    "أحمد بن سالم القاسمي",
    "يوسف بن سيف الهطالي",
    "راشد بن حمود البلوشي",
    "محمود بن خليفة الحبسي",
    "عبدالله بن محمد الحضرمي",
    "منصور بن سيف النبهاني",
    "بدر بن ناصر العبري",
    "حسن بن خالد الغافري",
    "إبراهيم بن سيف الزدجالي",
    "علي بن سعيد الفارسي",
    "جاسم بن خليفة العوفي",
    "طلال بن حمد السعدي",
    "سعود بن ناصر الحاتمي",
    "سالم بن علي البوسعيدي",
    "حمد بن سعيد الكندي",
    "ماجد بن خلفان الرواحي",
    "ناصر بن راشد الحارثي",
    "خالد بن محمد الشكيلي",
    "هيثم بن عبدالله المعمري",
    "سعيد بن حمد السيابي",
    "أحمد بن سالم القاسمي",
    "يوسف بن سيف الهطالي",
    "راشد بن حمود البلوشي",
    "محمود بن خليفة الحبسي",
    "عبدالله بن محمد الحضرمي",
    "منصور بن سيف النبهاني",
    "بدر بن ناصر العبري",
    "حسن بن خالد الغافري",
    "إبراهيم بن سيف الزدجالي",
    "علي بن سعيد الفارسي",
    "جاسم بن خليفة العوفي"
  ],
  "سادس 5": [
    "حمد بن سعيد الكندي",
    "ماجد بن خلفان الرواحي",
    "ناصر بن راشد الحارثي",
    "خالد بن محمد الشكيلي",
    "هيثم بن عبدالله المعمري",
    "سعيد بن حمد السيابي",
    "أحمد بن سالم القاسمي",
    "يوسف بن سيف الهطالي",
    "راشد بن حمود البلوشي",
    "محمود بن خليفة الحبسي",
    "عبدالله بن محمد الحضرمي",
    "منصور بن سيف النبهاني",
    "بدر بن ناصر العبري",
    "حسن بن خالد الغافري",
    "إبراهيم بن سيف الزدجالي",
    "علي بن سعيد الفارسي",
    "جاسم بن خليفة العوفي",
    "طلال بن حمد السعدي",
    "سعود بن ناصر الحاتمي",
    "سالم بن علي البوسعيدي",
    "حمد بن سعيد الكندي",
    "ماجد بن خلفان الرواحي",
    "ناصر بن راشد الحارثي",
    "خالد بن محمد الشكيلي",
    "هيثم بن عبدالله المعمري",
    "سعيد بن حمد السيابي",
    "أحمد بن سالم القاسمي",
    "يوسف بن سيف الهطالي",
    "راشد بن حمود البلوشي",
    "محمود بن خليفة الحبسي",
    "عبدالله بن محمد الحضرمي",
    "منصور بن سيف النبهاني",
    "بدر بن ناصر العبري",
    "حسن بن خالد الغافري",
    "إبراهيم بن سيف الزدجالي",
    "علي بن سعيد الفارسي"
  ],
  "سابع 1": [
    "حمد بن سعيد الكندي",
    "ماجد بن خلفان الرواحي",
    "ناصر بن راشد الحارثي",
    "خالد بن محمد الشكيلي",
    "هيثم بن عبدالله المعمري",
    "سعيد بن حمد السيابي",
    "أحمد بن سالم القاسمي",
    "يوسف بن سيف الهطالي",
    "راشد بن حمود البلوشي",
    "محمود بن خليفة الحبسي",
    "عبدالله بن محمد الحضرمي",
    "منصور بن سيف النبهاني",
    "بدر بن ناصر العبري",
    "حسن بن خالد الغافري",
    "إبراهيم بن سيف الزدجالي",
    "علي بن سعيد الفارسي",
    "جاسم بن خليفة العوفي",
    "طلال بن حمد السعدي",
    "سعود بن ناصر الحاتمي",
    "سالم بن علي البوسعيدي",
    "حمد بن سعيد الكندي",
    "ماجد بن خلفان الرواحي",
    "ناصر بن راشد الحارثي",
    "خالد بن محمد الشكيلي",
    "هيثم بن عبدالله المعمري",
    "سعيد بن حمد السيابي",
    "أحمد بن سالم القاسمي",
    "يوسف بن سيف الهطالي",
    "راشد بن حمود البلوشي",
    "محمود بن خليفة الحبسي",
    "عبدالله بن محمد الحضرمي",
    "منصور بن سيف النبهاني",
    "بدر بن ناصر العبري",
    "حسن بن خالد الغافري",
    "إبراهيم بن سيف الزدجالي",
    "علي بن سعيد الفارسي",
    "جاسم بن خليفة العوفي",
    "طلال بن حمد السعدي",
    "سعود بن ناصر الحاتمي"
  ],
  "سابع 2": [
    "حمد بن سعيد الكندي",
    "ماجد بن خلفان الرواحي",
    "ناصر بن راشد الحارثي",
    "خالد بن محمد الشكيلي",
    "هيثم بن عبدالله المعمري",
    "سعيد بن حمد السيابي",
    "أحمد بن سالم القاسمي",
    "يوسف بن سيف الهطالي",
    "راشد بن حمود البلوشي",
    "محمود بن خليفة الحبسي",
    "عبدالله بن محمد الحضرمي",
    "منصور بن سيف النبهاني",
    "بدر بن ناصر العبري",
    "حسن بن خالد الغافري",
    "إبراهيم بن سيف الزدجالي",
    "علي بن سعيد الفارسي",
    "جاسم بن خليفة العوفي",
    "طلال بن حمد السعدي",
    "سعود بن ناصر الحاتمي",
    "سالم بن علي البوسعيدي",
    "حمد بن سعيد الكندي",
    "ماجد بن خلفان الرواحي",
    "ناصر بن راشد الحارثي",
    "خالد بن محمد الشكيلي",
    "هيثم بن عبدالله المعمري",
    "سعيد بن حمد السيابي",
    "أحمد بن سالم القاسمي",
    "يوسف بن سيف الهطالي",
    "راشد بن حمود البلوشي",
    "محمود بن خليفة الحبسي",
    "عبدالله بن محمد الحضرمي",
    "منصور بن سيف النبهاني",
    "بدر بن ناصر العبري",
    "حسن بن خالد الغافري",
    "إبراهيم بن سيف الزدجالي",
    "علي بن سعيد الفارسي",
    "جاسم بن خليفة العوفي",
    "طلال بن حمد السعدي",
    "سعود بن ناصر الحاتمي",
    "سالم بن علي البوسعيدي"
  ],
  "سابع 3": [
    "حمد بن سعيد الكندي",
    "ماجد بن خلفان الرواحي",
    "ناصر بن راشد الحارثي",
    "خالد بن محمد الشكيلي",
    "هيثم بن عبدالله المعمري",
    "سعيد بن حمد السيابي",
    "أحمد بن سالم القاسمي",
    "يوسف بن سيف الهطالي",
    "راشد بن حمود البلوشي",
    "محمود بن خليفة الحبسي",
    "عبدالله بن محمد الحضرمي",
    "منصور بن سيف النبهاني",
    "بدر بن ناصر العبري",
    "حسن بن خالد الغافري",
    "إبراهيم بن سيف الزدجالي",
    "علي بن سعيد الفارسي",
    "جاسم بن خليفة العوفي",
    "طلال بن حمد السعدي",
    "سعود بن ناصر الحاتمي",
    "سالم بن علي البوسعيدي",
    "حمد بن سعيد الكندي",
    "ماجد بن خلفان الرواحي",
    "ناصر بن راشد الحارثي",
    "خالد بن محمد الشكيلي",
    "هيثم بن عبدالله المعمري",
    "سعيد بن حمد السيابي",
    "أحمد بن سالم القاسمي",
    "يوسف بن سيف الهطالي",
    "راشد بن حمود البلوشي",
    "محمود بن خليفة الحبسي",
    "عبدالله بن محمد الحضرمي",
    "منصور بن سيف النبهاني",
    "بدر بن ناصر العبري",
    "حسن بن خالد الغافري",
    "إبراهيم بن سيف الزدجالي",
    "علي بن سعيد الفارسي",
    "جاسم بن خليفة العوفي"
  ],
  "سابع 4": [
    "حمد بن سعيد الكندي",
    "ماجد بن خلفان الرواحي",
    "ناصر بن راشد الحارثي",
    "خالد بن محمد الشكيلي",
    "هيثم بن عبدالله المعمري",
    "سعيد بن حمد السيابي",
    "أحمد بن سالم القاسمي",
    "يوسف بن سيف الهطالي",
    "راشد بن حمود البلوشي",
    "محمود بن خليفة الحبسي",
    "عبدالله بن محمد الحضرمي",
    "منصور بن سيف النبهاني",
    "بدر بن ناصر العبري",
    "حسن بن خالد الغافري",
    "إبراهيم بن سيف الزدجالي",
    "علي بن سعيد الفارسي",
    "جاسم بن خليفة العوفي",
    "طلال بن حمد السعدي",
    "سعود بن ناصر الحاتمي",
    "سالم بن علي البوسعيدي",
    "حمد بن سعيد الكندي",
    "ماجد بن خلفان الرواحي",
    "ناصر بن راشد الحارثي",
    "خالد بن محمد الشكيلي",
    "هيثم بن عبدالله المعمري",
    "سعيد بن حمد السيابي",
    "أحمد بن سالم القاسمي",
    "يوسف بن سيف الهطالي",
    "راشد بن حمود البلوشي",
    "محمود بن خليفة الحبسي",
    "عبدالله بن محمد الحضرمي",
    "منصور بن سيف النبهاني",
    "بدر بن ناصر العبري",
    "حسن بن خالد الغافري",
    "إبراهيم بن سيف الزدجالي",
    "علي بن سعيد الفارسي",
    "جاسم بن خليفة العوفي",
    "طلال بن حمد السعدي",
    "سعود بن ناصر الحاتمي",
    "سالم بن علي البوسعيدي"
  ],
  "ثامن 1": [
    "حمد بن سعيد الكندي",
    "ماجد بن خلفان الرواحي",
    "ناصر بن راشد الحارثي",
    "خالد بن محمد الشكيلي",
    "هيثم بن عبدالله المعمري",
    "سعيد بن حمد السيابي",
    "أحمد بن سالم القاسمي",
    "يوسف بن سيف الهطالي",
    "راشد بن حمود البلوشي",
    "محمود بن خليفة الحبسي",
    "عبدالله بن محمد الحضرمي",
    "منصور بن سيف النبهاني",
    "بدر بن ناصر العبري",
    "حسن بن خالد الغافري",
    "إبراهيم بن سيف الزدجالي",
    "علي بن سعيد الفارسي",
    "جاسم بن خليفة العوفي",
    "طلال بن حمد السعدي",
    "سعود بن ناصر الحاتمي",
    "سالم بن علي البوسعيدي",
    "حمد بن سعيد الكندي",
    "ماجد بن خلفان الرواحي",
    "ناصر بن راشد الحارثي",
    "خالد بن محمد الشكيلي",
    "هيثم بن عبدالله المعمري",
    "سعيد بن حمد السيابي",
    "أحمد بن سالم القاسمي",
    "يوسف بن سيف الهطالي",
    "راشد بن حمود البلوشي",
    "محمود بن خليفة الحبسي",
    "عبدالله بن محمد الحضرمي",
    "منصور بن سيف النبهاني",
    "بدر بن ناصر العبري",
    "حسن بن خالد الغافري",
    "إبراهيم بن سيف الزدجالي",
    "علي بن سعيد الفارسي",
    "جاسم بن خليفة العوفي"
  ],
  "ثامن 2": [
    "حمد بن سعيد الكندي",
    "ماجد بن خلفان الرواحي",
    "ناصر بن راشد الحارثي",
    "خالد بن محمد الشكيلي",
    "هيثم بن عبدالله المعمري",
    "سعيد بن حمد السيابي",
    "أحمد بن سالم القاسمي",
    "يوسف بن سيف الهطالي",
    "راشد بن حمود البلوشي",
    "محمود بن خليفة الحبسي",
    "عبدالله بن محمد الحضرمي",
    "منصور بن سيف النبهاني",
    "بدر بن ناصر العبري",
    "حسن بن خالد الغافري",
    "إبراهيم بن سيف الزدجالي",
    "علي بن سعيد الفارسي",
    "جاسم بن خليفة العوفي",
    "طلال بن حمد السعدي",
    "سعود بن ناصر الحاتمي",
    "سالم بن علي البوسعيدي",
    "حمد بن سعيد الكندي",
    "ماجد بن خلفان الرواحي",
    "ناصر بن راشد الحارثي",
    "خالد بن محمد الشكيلي",
    "هيثم بن عبدالله المعمري",
    "سعيد بن حمد السيابي",
    "أحمد بن سالم القاسمي",
    "يوسف بن سيف الهطالي",
    "راشد بن حمود البلوشي",
    "محمود بن خليفة الحبسي",
    "عبدالله بن محمد الحضرمي",
    "منصور بن سيف النبهاني",
    "بدر بن ناصر العبري",
    "حسن بن خالد الغافري"
  ],
  "ثامن 3": [
    "حمد بن سعيد الكندي",
    "ماجد بن خلفان الرواحي",
    "ناصر بن راشد الحارثي",
    "خالد بن محمد الشكيلي",
    "هيثم بن عبدالله المعمري",
    "سعيد بن حمد السيابي",
    "أحمد بن سالم القاسمي",
    "يوسف بن سيف الهطالي",
    "راشد بن حمود البلوشي",
    "محمود بن خليفة الحبسي",
    "عبدالله بن محمد الحضرمي",
    "منصور بن سيف النبهاني",
    "بدر بن ناصر العبري",
    "حسن بن خالد الغافري",
    "إبراهيم بن سيف الزدجالي",
    "علي بن سعيد الفارسي",
    "جاسم بن خليفة العوفي",
    "طلال بن حمد السعدي",
    "سعود بن ناصر الحاتمي",
    "سالم بن علي البوسعيدي",
    "حمد بن سعيد الكندي",
    "ماجد بن خلفان الرواحي",
    "ناصر بن راشد الحارثي",
    "خالد بن محمد الشكيلي",
    "هيثم بن عبدالله المعمري",
    "سعيد بن حمد السيابي",
    "أحمد بن سالم القاسمي",
    "يوسف بن سيف الهطالي",
    "راشد بن حمود البلوشي",
    "محمود بن خليفة الحبسي",
    "عبدالله بن محمد الحضرمي",
    "منصور بن سيف النبهاني",
    "بدر بن ناصر العبري",
    "حسن بن خالد الغافري",
    "إبراهيم بن سيف الزدجالي",
    "علي بن سعيد الفارسي"
  ],
  "ثامن 4": [
    "حمد بن سعيد الكندي",
    "ماجد بن خلفان الرواحي",
    "ناصر بن راشد الحارثي",
    "خالد بن محمد الشكيلي",
    "هيثم بن عبدالله المعمري",
    "سعيد بن حمد السيابي",
    "أحمد بن سالم القاسمي",
    "يوسف بن سيف الهطالي",
    "راشد بن حمود البلوشي",
    "محمود بن خليفة الحبسي",
    "عبدالله بن محمد الحضرمي",
    "منصور بن سيف النبهاني",
    "بدر بن ناصر العبري",
    "حسن بن خالد الغافري",
    "إبراهيم بن سيف الزدجالي",
    "علي بن سعيد الفارسي",
    "جاسم بن خليفة العوفي",
    "طلال بن حمد السعدي",
    "سعود بن ناصر الحاتمي",
    "سالم بن علي البوسعيدي",
    "حمد بن سعيد الكندي",
    "ماجد بن خلفان الرواحي",
    "ناصر بن راشد الحارثي",
    "خالد بن محمد الشكيلي",
    "هيثم بن عبدالله المعمري",
    "سعيد بن حمد السيابي",
    "أحمد بن سالم القاسمي",
    "يوسف بن سيف الهطالي",
    "راشد بن حمود البلوشي",
    "محمود بن خليفة الحبسي",
    "عبدالله بن محمد الحضرمي",
    "منصور بن سيف النبهاني",
    "بدر بن ناصر العبري",
    "حسن بن خالد الغافري"
  ],
  "تاسع 1": [
    "حمد بن سعيد الكندي",
    "ماجد بن خلفان الرواحي",
    "ناصر بن راشد الحارثي",
    "خالد بن محمد الشكيلي",
    "هيثم بن عبدالله المعمري",
    "سعيد بن حمد السيابي",
    "أحمد بن سالم القاسمي",
    "يوسف بن سيف الهطالي",
    "راشد بن حمود البلوشي",
    "محمود بن خليفة الحبسي",
    "عبدالله بن محمد الحضرمي",
    "منصور بن سيف النبهاني",
    "بدر بن ناصر العبري",
    "حسن بن خالد الغافري",
    "إبراهيم بن سيف الزدجالي",
    "علي بن سعيد الفارسي",
    "جاسم بن خليفة العوفي",
    "طلال بن حمد السعدي",
    "سعود بن ناصر الحاتمي",
    "سالم بن علي البوسعيدي",
    "حمد بن سعيد الكندي",
    "ماجد بن خلفان الرواحي",
    "ناصر بن راشد الحارثي",
    "خالد بن محمد الشكيلي",
    "هيثم بن عبدالله المعمري",
    "سعيد بن حمد السيابي",
    "أحمد بن سالم القاسمي",
    "يوسف بن سيف الهطالي",
    "راشد بن حمود البلوشي",
    "محمود بن خليفة الحبسي",
    "عبدالله بن محمد الحضرمي",
    "منصور بن سيف النبهاني",
    "بدر بن ناصر العبري",
    "حسن بن خالد الغافري",
    "إبراهيم بن سيف الزدجالي",
    "علي بن سعيد الفارسي",
    "جاسم بن خليفة العوفي",
    "طلال بن حمد السعدي",
    "سعود بن ناصر الحاتمي"
  ],
  "تاسع 2": [
    "حمد بن سعيد الكندي",
    "ماجد بن خلفان الرواحي",
    "ناصر بن راشد الحارثي",
    "خالد بن محمد الشكيلي",
    "هيثم بن عبدالله المعمري",
    "سعيد بن حمد السيابي",
    "أحمد بن سالم القاسمي",
    "يوسف بن سيف الهطالي",
    "راشد بن حمود البلوشي",
    "محمود بن خليفة الحبسي",
    "عبدالله بن محمد الحضرمي",
    "منصور بن سيف النبهاني",
    "بدر بن ناصر العبري",
    "حسن بن خالد الغافري",
    "إبراهيم بن سيف الزدجالي",
    "علي بن سعيد الفارسي",
    "جاسم بن خليفة العوفي",
    "طلال بن حمد السعدي",
    "سعود بن ناصر الحاتمي",
    "سالم بن علي البوسعيدي",
    "حمد بن سعيد الكندي",
    "ماجد بن خلفان الرواحي",
    "ناصر بن راشد الحارثي",
    "خالد بن محمد الشكيلي",
    "هيثم بن عبدالله المعمري",
    "سعيد بن حمد السيابي",
    "أحمد بن سالم القاسمي",
    "يوسف بن سيف الهطالي",
    "راشد بن حمود البلوشي",
    "محمود بن خليفة الحبسي",
    "عبدالله بن محمد الحضرمي",
    "منصور بن سيف النبهاني",
    "بدر بن ناصر العبري",
    "حسن بن خالد الغافري",
    "إبراهيم بن سيف الزدجالي",
    "علي بن سعيد الفارسي",
    "جاسم بن خليفة العوفي",
    "طلال بن حمد السعدي",
    "سعود بن ناصر الحاتمي"
  ],
  "تاسع 3": [
    "حمد بن سعيد الكندي",
    "ماجد بن خلفان الرواحي",
    "ناصر بن راشد الحارثي",
    "خالد بن محمد الشكيلي",
    "هيثم بن عبدالله المعمري",
    "سعيد بن حمد السيابي",
    "أحمد بن سالم القاسمي",
    "يوسف بن سيف الهطالي",
    "راشد بن حمود البلوشي",
    "محمود بن خليفة الحبسي",
    "عبدالله بن محمد الحضرمي",
    "منصور بن سيف النبهاني",
    "بدر بن ناصر العبري",
    "حسن بن خالد الغافري",
    "إبراهيم بن سيف الزدجالي",
    "علي بن سعيد الفارسي",
    "جاسم بن خليفة العوفي",
    "طلال بن حمد السعدي",
    "سعود بن ناصر الحاتمي",
    "سالم بن علي البوسعيدي",
    "حمد بن سعيد الكندي",
    "ماجد بن خلفان الرواحي",
    "ناصر بن راشد الحارثي",
    "خالد بن محمد الشكيلي",
    "هيثم بن عبدالله المعمري",
    "سعيد بن حمد السيابي",
    "أحمد بن سالم القاسمي",
    "يوسف بن سيف الهطالي",
    "راشد بن حمود البلوشي",
    "محمود بن خليفة الحبسي",
    "عبدالله بن محمد الحضرمي",
    "منصور بن سيف النبهاني",
    "بدر بن ناصر العبري",
    "حسن بن خالد الغافري",
    "إبراهيم بن سيف الزدجالي",
    "علي بن سعيد الفارسي",
    "جاسم بن خليفة العوفي",
    "طلال بن حمد السعدي",
    "سعود بن ناصر الحاتمي"
  ],
  "تاسع 4": [
    "حمد بن سعيد الكندي",
    "ماجد بن خلفان الرواحي",
    "ناصر بن راشد الحارثي",
    "خالد بن محمد الشكيلي",
    "هيثم بن عبدالله المعمري",
    "سعيد بن حمد السيابي",
    "أحمد بن سالم القاسمي",
    "يوسف بن سيف الهطالي",
    "راشد بن حمود البلوشي",
    "محمود بن خليفة الحبسي",
    "عبدالله بن محمد الحضرمي",
    "منصور بن سيف النبهاني",
    "بدر بن ناصر العبري",
    "حسن بن خالد الغافري",
    "إبراهيم بن سيف الزدجالي",
    "علي بن سعيد الفارسي",
    "جاسم بن خليفة العوفي",
    "طلال بن حمد السعدي",
    "سعود بن ناصر الحاتمي",
    "سالم بن علي البوسعيدي",
    "حمد بن سعيد الكندي",
    "ماجد بن خلفان الرواحي",
    "ناصر بن راشد الحارثي",
    "خالد بن محمد الشكيلي",
    "هيثم بن عبدالله المعمري",
    "سعيد بن حمد السيابي",
    "أحمد بن سالم القاسمي",
    "يوسف بن سيف الهطالي",
    "راشد بن حمود البلوشي",
    "محمود بن خليفة الحبسي",
    "عبدالله بن محمد الحضرمي"
  ],
  "تاسع 5": [
    "حمد بن سعيد الكندي",
    "ماجد بن خلفان الرواحي",
    "ناصر بن راشد الحارثي",
    "خالد بن محمد الشكيلي",
    "هيثم بن عبدالله المعمري",
    "سعيد بن حمد السيابي",
    "أحمد بن سالم القاسمي",
    "يوسف بن سيف الهطالي",
    "راشد بن حمود البلوشي",
    "محمود بن خليفة الحبسي",
    "عبدالله بن محمد الحضرمي",
    "منصور بن سيف النبهاني",
    "بدر بن ناصر العبري",
    "حسن بن خالد الغافري",
    "إبراهيم بن سيف الزدجالي",
    "علي بن سعيد الفارسي",
    "جاسم بن خليفة العوفي",
    "طلال بن حمد السعدي",
    "سعود بن ناصر الحاتمي",
    "سالم بن علي البوسعيدي",
    "حمد بن سعيد الكندي",
    "ماجد بن خلفان الرواحي",
    "ناصر بن راشد الحارثي",
    "خالد بن محمد الشكيلي",
    "هيثم بن عبدالله المعمري",
    "سعيد بن حمد السيابي",
    "أحمد بن سالم القاسمي",
    "يوسف بن سيف الهطالي",
    "راشد بن حمود البلوشي",
    "محمود بن خليفة الحبسي",
    "عبدالله بن محمد الحضرمي"
  ]
}